torch_delaunay/_C.cpython-312-darwin.so
torch_delaunay/__init__.py
torch_delaunay/functional.py
torch_delaunay/functional_test.py
torch_delaunay/py.typed
torch_delaunay-1.3.0.dist-info/LICENSE
torch_delaunay-1.3.0.dist-info/METADATA
torch_delaunay-1.3.0.dist-info/WHEEL
torch_delaunay-1.3.0.dist-info/top_level.txt
torch_delaunay-1.3.0.dist-info/RECORD
